odoo8_addon_mrp_production_raw_material_procurement_group-8.0.1.0.0.99.dev11-py2.7-nspkg.pth
odoo8_addon_mrp_production_raw_material_procurement_group-8.0.1.0.0.99.dev11.dist-info/DESCRIPTION.rst
odoo8_addon_mrp_production_raw_material_procurement_group-8.0.1.0.0.99.dev11.dist-info/METADATA
odoo8_addon_mrp_production_raw_material_procurement_group-8.0.1.0.0.99.dev11.dist-info/RECORD
odoo8_addon_mrp_production_raw_material_procurement_group-8.0.1.0.0.99.dev11.dist-info/WHEEL
odoo8_addon_mrp_production_raw_material_procurement_group-8.0.1.0.0.99.dev11.dist-info/metadata.json
odoo8_addon_mrp_production_raw_material_procurement_group-8.0.1.0.0.99.dev11.dist-info/namespace_packages.txt
odoo8_addon_mrp_production_raw_material_procurement_group-8.0.1.0.0.99.dev11.dist-info/top_level.txt
odoo_addons/mrp_production_raw_material_procurement_group/README.rst
odoo_addons/mrp_production_raw_material_procurement_group/__init__.py
odoo_addons/mrp_production_raw_material_procurement_group/__openerp__.py
odoo_addons/mrp_production_raw_material_procurement_group/i18n/de.po
odoo_addons/mrp_production_raw_material_procurement_group/i18n/es.po
odoo_addons/mrp_production_raw_material_procurement_group/i18n/es_MX.po
odoo_addons/mrp_production_raw_material_procurement_group/i18n/fr.po
odoo_addons/mrp_production_raw_material_procurement_group/i18n/gl.po
odoo_addons/mrp_production_raw_material_procurement_group/i18n/hr.po
odoo_addons/mrp_production_raw_material_procurement_group/i18n/it.po
odoo_addons/mrp_production_raw_material_procurement_group/i18n/mrp_production_raw_material_procurement_group.pot
odoo_addons/mrp_production_raw_material_procurement_group/i18n/pt_BR.po
odoo_addons/mrp_production_raw_material_procurement_group/i18n/ro.po
odoo_addons/mrp_production_raw_material_procurement_group/i18n/sl.po
odoo_addons/mrp_production_raw_material_procurement_group/i18n/tr.po
odoo_addons/mrp_production_raw_material_procurement_group/i18n/vi_VN.po
odoo_addons/mrp_production_raw_material_procurement_group/i18n/zh_CN.po
odoo_addons/mrp_production_raw_material_procurement_group/models/__init__.py
odoo_addons/mrp_production_raw_material_procurement_group/models/mrp_production.py
odoo_addons/mrp_production_raw_material_procurement_group/static/description/icon.png
odoo_addons/mrp_production_raw_material_procurement_group/tests/__init__.py
odoo_addons/mrp_production_raw_material_procurement_group/tests/test_mrp_production.py
odoo_addons/mrp_production_raw_material_procurement_group/views/mrp_production_views.xml
